iammeter/__init__.py
iammeter/client.py
iammeter/power_meter.py
iammeter-0.2.1.dist-info/DESCRIPTION.rst
iammeter-0.2.1.dist-info/METADATA
iammeter-0.2.1.dist-info/RECORD
iammeter-0.2.1.dist-info/WHEEL
iammeter-0.2.1.dist-info/metadata.json
iammeter-0.2.1.dist-info/top_level.txt
