Metadata-Version: 2.0
Name: iammeter
Version: 0.2.1
Summary: IamMeter api
Home-page: https://github.com/lewei50/iammeter_pip_lib
Author: yangbo1979
Author-email: gyangbo@gmail.com
License: UNKNOWN
Platform: UNKNOWN
Classifier: Programming Language :: Python :: 3
Classifier: License :: OSI Approved :: MIT License
Classifier: Operating System :: OS Independent
